bag.py
cli.py
config_constrainer.py
dependencies.py
pony.py
pony_scons.py
pony_express-0.2.5a1.data/scripts/pony.py
pony_express-0.2.5a1.dist-info/DESCRIPTION.rst
pony_express-0.2.5a1.dist-info/METADATA
pony_express-0.2.5a1.dist-info/RECORD
pony_express-0.2.5a1.dist-info/WHEEL
pony_express-0.2.5a1.dist-info/metadata.json
pony_express-0.2.5a1.dist-info/top_level.txt
