Metadata-Version: 2.0
Name: pony-express
Version: 0.2.5a1
Summary: General purpose package and dependency manager based on MongoDB
Home-page: https://github.com/gpuoti/Artifact-PonyExpress
Author: Giuseppe Puoti
Author-email: giuseppe.puoti@gmail.com
License: LGPL-3
Platform: UNKNOWN
Classifier: Development Status :: 3 - Alpha
Classifier: Topic :: Software Development :: Version Control
Classifier: Topic :: System :: Archiving :: Packaging
Classifier: License :: OSI Approved :: GNU Lesser General Public License v3 (LGPLv3)
Requires-Dist: colorama
Requires-Dist: networkx
Requires-Dist: pymongo
Requires-Dist: tabulate
